src/amm/__init__.py
src/amm/main.py
amm-0.0.1.dist-info/METADATA
amm-0.0.1.dist-info/WHEEL
amm-0.0.1.dist-info/top_level.txt
amm-0.0.1.dist-info/RECORD
