Metadata-Version: 2.1
Name: amm
Version: 0.0.1
Summary: AI Model Manager
Home-page: https://github.com/blaesus/amm
Author: Andy Shu
Author-email: shu@immux.com
Classifier: Programming Language :: Python :: 3
Classifier: License :: OSI Approved :: MIT License
Classifier: Operating System :: OS Independent
Requires-Python: >=3.6
